LICENSE.md
MANIFEST.in
README.rst
setup.cfg
setup.py
medux/plugins/cashbook/__init__.py
medux/plugins/cashbook/admin.py
medux/plugins/cashbook/apps.py
medux/plugins/cashbook/conf.py
medux/plugins/cashbook/menus.py
medux/plugins/cashbook/models.py
medux/plugins/cashbook/tests.py
medux/plugins/cashbook/urls.py
medux/plugins/cashbook/api/__init__.py
medux/plugins/cashbook/api/interfaces.py
medux/plugins/cashbook/locale/de/LC_MESSAGES/django.mo
medux/plugins/cashbook/locale/de/LC_MESSAGES/django.po
medux/plugins/cashbook/migrations/0001_initial.py
medux/plugins/cashbook/migrations/__init__.py
medux/plugins/cashbook/reflexes/__init__.py
medux/plugins/cashbook/reflexes/cashbook_reflex.py
medux/plugins/cashbook/static/cashbook/.gitkeep
medux/plugins/cashbook/templates/cashbook/.gitkeep
medux/plugins/cashbook/templates/cashbook/accountactivities.html
medux/plugins/cashbook/templates/cashbook/base.html
medux/plugins/cashbook/tests/conftest.py
medux/plugins/cashbook/tests/test_main.py
medux/plugins/cashbook/views/__init__.py
medux_cashbook.egg-info/PKG-INFO
medux_cashbook.egg-info/SOURCES.txt
medux_cashbook.egg-info/dependency_links.txt
medux_cashbook.egg-info/entry_points.txt
medux_cashbook.egg-info/namespace_packages.txt
medux_cashbook.egg-info/not-zip-safe
medux_cashbook.egg-info/requires.txt
medux_cashbook.egg-info/top_level.txt