Metadata-Version: 2.1
Name: medux-cashbook
Version: 0.0.2
Summary: "A simple Cashbook plugin for MedUX."
Home-page: https://www.medux.at
Author: Christian González
Author-email: christian.gonzalez@nerdocs.at
License: AGPL-3.0-or-later
Platform: UNKNOWN
Classifier: Development Status :: 3 - Alpha
Classifier: Environment :: Web Environment
Classifier: Framework :: Django :: 3.2
Classifier: Intended Audience :: Developers
Classifier: License :: OSI Approved :: GNU Affero General Public License v3 or later (AGPLv3+)
Classifier: Natural Language :: English
Classifier: Operating System :: OS Independent
Classifier: Programming Language :: Python :: 3 :: Only
Classifier: Programming Language :: Python :: 3.6
Classifier: Programming Language :: JavaScript
Classifier: Topic :: Internet :: WWW/HTTP
Classifier: Topic :: Internet :: WWW/HTTP :: Dynamic Content
Requires-Python: >=3.6
Provides-Extra: dev
License-File: LICENSE.md
